odoo10_addon_medical_pathology_icd10-10.0.1.0.0-py2.7-nspkg.pth
odoo/addons/medical_pathology_icd10/README.rst
odoo/addons/medical_pathology_icd10/__init__.py
odoo/addons/medical_pathology_icd10/__manifest__.py
odoo/addons/medical_pathology_icd10/demo/medical_pathology_import.xml
odoo/addons/medical_pathology_icd10/static/description/icon.png
odoo/addons/medical_pathology_icd10/tests/__init__.py
odoo/addons/medical_pathology_icd10/tests/test_medical_pathology_import.py
odoo/addons/medical_pathology_icd10/wizards/__init__.py
odoo/addons/medical_pathology_icd10/wizards/medical_pathology_import.py
odoo10_addon_medical_pathology_icd10-10.0.1.0.0.dist-info/DESCRIPTION.rst
odoo10_addon_medical_pathology_icd10-10.0.1.0.0.dist-info/METADATA
odoo10_addon_medical_pathology_icd10-10.0.1.0.0.dist-info/RECORD
odoo10_addon_medical_pathology_icd10-10.0.1.0.0.dist-info/WHEEL
odoo10_addon_medical_pathology_icd10-10.0.1.0.0.dist-info/metadata.json
odoo10_addon_medical_pathology_icd10-10.0.1.0.0.dist-info/namespace_packages.txt
odoo10_addon_medical_pathology_icd10-10.0.1.0.0.dist-info/top_level.txt
